pyenvloadermeta/__init__.py
pyenvloadermeta-1.0.2.dist-info/METADATA
pyenvloadermeta-1.0.2.dist-info/WHEEL
pyenvloadermeta-1.0.2.dist-info/top_level.txt
pyenvloadermeta-1.0.2.dist-info/RECORD
