Metadata-Version: 2.1
Name: pyenvloadermeta
Version: 1.0.2
Summary: A metaclass for automatically loading and converting environment variables.
Home-page: https://github.com/Praveensenpai/pyenvloadermeta
Author: Praveen
Author-email: pvnt20@gmail.com
Requires-Python: >=3.10
Requires-Dist: python-dotenv>=1.0.1
